{
  "source_file": "rapor2023.txt",
  "category": "ozel",
  "chunk_index": 472,
  "chunk_text": "Bu süreçte, transfer merkezine uğramadan ayrıştırma işlemlerinin yapılabileceği şekilde donatılmış araçların (mobil platformlar) Sayfa 52 / 99 kullanılması verimliliği arttırıcı bir seçenek olarak düşünülmektedir. Bu çerçevede, mobil platformların hizmet vereceği alanda kapsama boşluklarının olmaması ve süreçte yeni oluşacak (dinamik) taleplerin de karşılanabilmesi gerekmektedir (Amiri ve Salari, 2019).",
  "char_len": 406,
  "sentence_count": 2
}