{
  "source_file": "rapor2023.txt",
  "category": "genel",
  "chunk_index": 98,
  "chunk_text": "Faaliyet Döneminde Devam Eden Proje Detayları Proje Kodu HX-00004 Proje Adı Zaman Pencereli ve Hızlı Teslimatlarda Optimizasyon ve Kapasite Yönetimi Proje 1.1.2019 Başlama Tarihi Proje Bitiş 30.6.2021 Tarihi Projede 16 Görev Alan Personel Sayısı Proje Süresi 240 (Adam Ay) Ulusal 3.1.1. 1501 Sanayi Ar-Ge Projeleri Destekleme Programı Destek Programı Uluslararası Destek Programı Toplam 3.950.000,00 Proje Bütçesi (TL) Öz 3.332.012,79 Kaynaklarca Karşılanan Tutar (TL) Destek 617.987,21 Tutarı (TL) Hizmet Alım Akademik Danışmanlık Konusu Hizmet Yurt İçi Alımı (Yurtiçi / Yurtdışı) Toplam 72.000,00 Hizmet Alımı Tutarı (TL) Sayfa 40 / 99 Yurt İçi 72.000,00 Hizmet Alımı Tutarı (TL) Yurt Dışı 0,00 Hizmet Alımı Tutarı (TL) Proje E-ticaret ürünlerinin teslimatlarında zaman pencerelerinin daralması ve hızlı teslimat beklentisi günden güne Konusunu artmaktadır. PwC’nin 2018 yılı Global Müşteri Beklentileri Anketi’ne göre, tüketicilerin %40’ı aynı gün ve hızlı Belirleyen teslimat için fazladan para ödemeye isteklidir. Buna ek olarak %25’i 1-2 saatlik spesifik zaman aralıklarında İhtiyaçlar teslim almak istemektedir. Değişen tüketici beklentilerine uygun olarak, HepsiJET’in market ürünlerinin e- teslimat hizmetlerinde zaman pencerelerini daraltmak ve saatlik teslimat hizmeti sunulması ihtiyacı doğmuştur. Bu hizmetlerin son tüketiciye taahhüt edilen zamanda sunulabilmesi için mevcut hizmetler ile entegre sunulması için gerekli altyapının kurulması ve optimizasyon algoritmaları ile desteklenmesi çalışmaları gerekmektedir.",
  "char_len": 1529,
  "sentence_count": 5
}