{
  "source_file": "rapor2023.txt",
  "category": "mevzuat",
  "chunk_index": 211,
  "chunk_text": "Bu kapsamda mikroservis mimari dönüşümü, front-end teknoloji dönüşümü, dispatch(dağıt) fonksiyonu revizyonu ve test otomasyonu teknolojilerinin kurulumunun yapılması hedeflenmiştir. İş paketi kapsamında yapılacak çalışmaları sistem güvenlik, entegrasyon ve yük testleri takip edecektir. Sistemin herhangi bir yavaşlama ya da duraklama olmaksızın yüzbinlerce paketin taşımasına elverişli halde olması ve bu süreçte dışa bağımlı yapılar yerine kendi yeteneklerimiz ile ölçeklenebilir yapılar kurulması hedeflenmiştir. Projenin - Projede proje yönetim ve iş, hata takip yazılımı olarak Atlassian Jira, kaynak kod yönetim sistemi olarak Git, Yenilikçi sürekli tümleştirme (Continuous Integration) aracı olarak da Jenkins kullanılmaktadır. Kod gözden geçirme Yönü ve Ar- süreçleri için Bitbucket kullanılmaktadır. İstemci tarafı teknolojileri olarak HTML5, CSS3, Javascript, Angular 5, Ge Niteliği React, sunucu tarafı teknolojileri olarak, SpringBoot, Hibernate, Node.js, PostgreSQL kulanılmaktadır. - Projede makine öğrenmesi teknikleri ile kapasite tahminleme, rota optimizasyonu ve doğal dil işleme algoritmalarının kullanımı ile büyük ölçekli operasyonlarda katma değerli hizmetlerin sunulması hedeflenmiştir. - Mobil teknolojilerin kullanımı ile süreçlerin uçtan uca takibi yapılabilecek ve olası kayıp/hasarların önüne geçilebilecektir.",
  "char_len": 1338,
  "sentence_count": 6
}