{
  "source_file": "rapor2023.txt",
  "category": "mevzuat",
  "chunk_index": 146,
  "chunk_text": "İş paketi kapsamında Dar Zaman Aralıkları İçin Çoklu Araç Optimizasyon Algoritması, E-ticaret Firmaları İçin Coğrafik Kapasite Slot Algoritması ve Dinamik Değişen Günlük Kapasite Planlama Algoritmaları geliştirmeleri devam etmektedir. Müşteri Hizmetleri Modülü Yeni iş modeli teslimatları mevcut iş modeline göre daha dinamik yapıda olacağından, müşteriden gelen taleplerin de aynı ölçüde dinamik olacağı öngörülmektedir. Bu yapıda gelen talep ve şikayetlerin hızlı çözülebilmesi için Müşteri Hizmetleri departmanına veri akışının sağlanması ve haberleşme asetlerinin iyileştirilmesi gerekmektedir. Bu nedenle senaryo analizleri yapılarak sistem buna uygun olarak tasarlanacaktır. Projede pilot çalışmalar stok tutan cep depolardan gıda ürünlerinin teslimatı ile başlamıştır. Gıda ürünlerinin taşınması operasyonunda müşteri hizmetleri tarafından aşağıdaki durumların yönetilmesi gerekmektedir; -Tedarik kaynaklı değişiklikler: Mağaza kaynaklı ürünlerin tedariği ya da toplanması sırasında yaşanan aksaklıklardır.",
  "char_len": 1013,
  "sentence_count": 6
}